mortal_ini/__init__.py
mortal_ini/ini_main.cp39-win_amd64.pyd
mortal_ini-4.2.0.dist-info/METADATA
mortal_ini-4.2.0.dist-info/WHEEL
mortal_ini-4.2.0.dist-info/top_level.txt
mortal_ini-4.2.0.dist-info/RECORD
